envelope/__init__.py
envelope/annot_model.py
envelope/binary.py
envelope/envelope.py
envelope/impl/__init__.py
envelope/impl/checker/__init__.py
envelope/impl/checker/cascade_checker.py
envelope/impl/checker/pipelines.py
envelope/impl/envelope_impl.py
envelope/impl/storage/__init__.py
envelope/impl/storage/express_to_network.py
envelope/impl/storage/mem_storage.py
envelope/impl/storage/sqlite3_storage.py
envelope/storage.py
ndn_lvs_envelope-0.1.1.dist-info/COPYING
ndn_lvs_envelope-0.1.1.dist-info/METADATA
ndn_lvs_envelope-0.1.1.dist-info/WHEEL
ndn_lvs_envelope-0.1.1.dist-info/RECORD
